lumivor/README.md
lumivor/__init__.py
lumivor/logging_config.py
lumivor/utils.py
lumivor/agent/prompts.py
lumivor/agent/service.py
lumivor/agent/tests.py
lumivor/agent/views.py
lumivor/agent/message_manager/service.py
lumivor/agent/message_manager/tests.py
lumivor/agent/message_manager/views.py
lumivor/browser/browser.py
lumivor/browser/context.py
lumivor/browser/views.py
lumivor/browser/tests/screenshot_test.py
lumivor/browser/tests/test_clicks.py
lumivor/controller/service.py
lumivor/controller/views.py
lumivor/controller/registry/service.py
lumivor/controller/registry/views.py
lumivor/dom/__init__.py
lumivor/dom/buildDomTree.js
lumivor/dom/service.py
lumivor/dom/views.py
lumivor/dom/history_tree_processor/service.py
lumivor/dom/history_tree_processor/view.py
lumivor/dom/tests/extraction_test.py
lumivor/dom/tests/process_dom_test.py
lumivor/telemetry/service.py
lumivor/telemetry/views.py
lumivor-0.1.8.dist-info/METADATA
lumivor-0.1.8.dist-info/WHEEL
lumivor-0.1.8.dist-info/licenses/LICENSE
lumivor-0.1.8.dist-info/RECORD
